filefilter/__init__.py
filefilter/collector.py
filefilter/ruleset.py
filefilter/utilities.py
filefilter-0.1.12.dist-info/licenses/LICENSE
filefilter-0.1.12.dist-info/METADATA
filefilter-0.1.12.dist-info/WHEEL
filefilter-0.1.12.dist-info/top_level.txt
filefilter-0.1.12.dist-info/RECORD
